graph-cyclone/__init__.py
graph-cyclone/graph-cyclone.py
graph_cyclone/__init__.py
graph_cyclone/graph-cyclone.py
graph_cyclone/graph_cyclone.py
graph_cyclone-1.3.dist-info/METADATA
graph_cyclone-1.3.dist-info/RECORD
graph_cyclone-1.3.dist-info/WHEEL
graph_cyclone-1.3.dist-info/top_level.txt
